{
  "count": 62,
  "description": "",
  "type": "image/png",
  "creationDate": 1701684283856,
  "title": "IMAGE/PNG",
  "url": "https://storage.googleapis.com/bracket-technologies.appspot.com/storage-acc/lrckS8hyKTBTuMFNwtTe?GoogleAccessId=firebase-adminsdk-kcrle%40bracket-technologies.iam.gserviceaccount.com&Expires=32509468800&Signature=VnqAKyzxChwr5a2V0gRx493mlgss5xUcedmnJ%2FgDxJz2qe58zCv%2BL2VoLLNDDOuUm0%2Bz7a3sStLHv434VNOTgx7lkfclFhdkIRfmUcxfhwbzDpEd5wEO9Zl2BQiVpIKaxWWygkrAjnl9A0JIGa020trXAboht%2Bzm5IjQzgrQn4PCGH17Znzn3RgU4hUDNDC0KFAu8jB9iLNXW56MMuZPSUbZpcqb8jl6qtCF7znP69UWXPc92eF%2FIgTgU8tLtGysSfrKbqLkjKplpXk4X2iDL9x98N15B9GpHlFkn11intqlPJrU%2BjJrue4oAwLkp%2B1vAOI8%2F6XIVtfajuJ89rSdwQ%3D%3D",
  "tags": [],
  "ref": "IMG-00000062",
  "size": 12107,
  "name": "notification.png",
  "lastModified": 1701684169214,
  "__props__": {
    "id": "m1F71098a8H8O740N1q922K0G3",
    "creationDate": 1701684176989,
    "collapsed": [],
    "comments": [],
    "docName": "lrckS8hyKTBTuMFNwtTe",
    "folderPath": [],
    "confidential": {
      "projectPublicID": "71j7R0d8Z8p7E0d0n081r1e854"
    }
  }
}