{
    "port": 84,
    "serverID": "G1K7B2Y4N5l8y8U839w9v3F586",
    "creationDate": 1724588899371,
    "closes": [],
    "__props__": {
        "id": "C1X7x2T4l5G8w8Y8H9y9G3f7z6",
        "doc": "runningServer134",
        "counter": 134,
        "creationDate": 1724588899376,
        "collection": "runningServer",
        "chunk": "chunk1",
        "lastModified": 1724588899376,
        "dev": false,
        "actions": {},
        "comments": [],
        "collapsed": [],
        "arrange": [],
        "secured": false,
        "size": 366
    }
}