{
    "port": 87,
    "serverID": "81x7J2o4L5p7j8X1h2m3i2K7j2",
    "creationDate": 1724578123284,
    "closes": [],
    "__props__": {
        "id": "k1V7H2I4q577p8o1e2H302l930",
        "doc": "runningServer105",
        "counter": 105,
        "creationDate": 1724578123290,
        "collection": "runningServer",
        "chunk": "chunk1",
        "lastModified": 1724578123290,
        "dev": false,
        "actions": {},
        "comments": [],
        "collapsed": [],
        "arrange": [],
        "secured": false,
        "size": 366
    }
}