{
    "port": 82,
    "serverID": "g137a2c3X1Q1l4x4r6L0J2W6d4",
    "creationDate": 1723114460301,
    "closes": [],
    "__props__": {
        "id": "h1t7Z2A3W1w1p4g43690e3O016",
        "doc": "runningServer31",
        "counter": 31,
        "creationDate": 1723114460306,
        "collection": "runningServer",
        "chunk": "chunk1",
        "lastModified": 1723114460306,
        "dev": false,
        "actions": {},
        "comments": [],
        "collapsed": [],
        "arrange": [],
        "secured": false,
        "size": 364
    }
}