{
    "port": 85,
    "serverID": "w1k732M4t5T0C863x5p9Z8L0L3",
    "creationDate": 1724508359821,
    "closes": [],
    "__props__": {
        "id": "Q107i2H4r5D0C8M3h5z9x8p266",
        "doc": "runningServer59",
        "counter": 59,
        "creationDate": 1724508359826,
        "collection": "runningServer",
        "chunk": "chunk1",
        "lastModified": 1724508359826,
        "dev": false,
        "actions": {},
        "comments": [],
        "collapsed": [],
        "arrange": [],
        "secured": false,
        "size": 364
    }
}