{
  "facilities": [
    "Free WiFi",
    "Restaurant",
    "Room service",
    "Bar",
    "24-hour front desk",
    "Sauna",
    "Fitness center",
    "Garden",
    "Terrace",
    "Non-smoking rooms",
    "Airport shuffle",
    "Family rooms",
    "Spa and wellness center",
    "Hot tub/Jacuzzi",
    "Air conditioning",
    "Water park",
    "Swimming pool"
  ],
  "__props__": {
    "id": "21I7k018p888E7M0X033E734Y5",
    "creationDate": 1688672698490,
    "collapsed": [],
    "comments": [],
    "docName": "mostPopularFacilities",
    "folderPath": [],
    "confidential": {
      "projectPublicID": "71j7R0d8Z8p7E0d0n081r1e854"
    }
  }
}