{
  "updateBy": "jTHiW6Ze96wxuZq2c7woB1o4YW7tjsz7mEK7rDruM3II7XZVFIaqCXgGKYyq1699560058406",
  "difference": [
    {
      "new": "8888",
      "path": "trainName",
      "old": "u8"
    }
  ],
  "description": "Data has been updated",
  "sheet": "aRiAoFpuKnap9rZCJcACccDMX29Kai3iT6kFHbYUfHtc2mL9kHAk3wzgai8g1699268378803",
  "creationDay": 1700611200000,
  "creationDate": 1700649640033,
  "__props__": {
    "id": "Z1t7j1B033F3Z0W7Y9S0J7o5y2",
    "doc": "NeSIhdtqpORqvBWNVkND7NfrcSWUnAGiRHCiBdIQ2bdcHwX8McjywejWpruG1700649640033",
    "creationDate": 1710330790752,
    "active": true,
    "createdByUserID": "41V7H078W8I8I780z1m9Y2E4Y2",
    "collapsed": [],
    "comments": [],
    "folderPath": [],
    "actions": {},
    "projectID": "f1m7R0f878N8V7g0c1w8W9u1C6",
    "counter": 1023
  }
}