{
  "description": "Default account",
  "creationDate": 1708687890566,
  "branch": "5nyQK1IEz87F9YeHrNBVqtOM9r8HFBu1dLNBXm1e9mvL4YgdweVh3ql6KPGE",
  "lastBalance": "CoI0bV5HnUKSHerRhUFR39TccPaeHVEoIXf6d8FAmkANixMxy4KxOAiOVmzt-1708687890566",
  "ref": "ACC-00000267",
  "ledgerAccount": "6890/1/1",
  "blockAccount": "No",
  "name": "Non Oper'tg Depreciations & Provisions",
  "currency": "USD",
  "creationDay": 1708646400000,
  "startsWith": [
    "6",
    "68",
    "689",
    "6890"
  ],
  "__props__": {
    "id": "J147z0c878x8V7w0l1C4r9l892",
    "creationDate": 1708687671675,
    "collapsed": [],
    "comments": [],
    "docName": "siYb52f9lohjFGITRXDM3kUdfno3LHtiP4I1JWPhfa2tBNF8l9LP4xBl4Djh-1708687890566",
    "folderPath": [],
    "confidential": {
      "projectPublicID": "71j7R0d8Z8p7E0d0n081r1e854"
    }
  }
}