{
  "description": "Default account",
  "creationDate": 1708687884370,
  "branch": "5nyQK1IEz87F9YeHrNBVqtOM9r8HFBu1dLNBXm1e9mvL4YgdweVh3ql6KPGE",
  "lastBalance": "6pwGT0LT4d370HAStQwyGsj1SYx65BsVeBxLUuCgN7p9BangolU049vMLska-1708687884369",
  "ref": "ACC-00000135",
  "ledgerAccount": "6553/1/1",
  "blockAccount": "No",
  "name": "Prov.Fr Dimunition In Value Of Inventory",
  "currency": "USD",
  "creationDay": 1708646400000,
  "startsWith": [
    "6",
    "65",
    "655",
    "6553"
  ],
  "__props__": {
    "id": "Y1W760J818h8V7I0o1i4k169d4",
    "creationDate": 1708687671675,
    "collapsed": [],
    "comments": [],
    "docName": "CIgBK6ia81k5mBOH72XGJin4lifqb9meuQiiuKcdurwtArS3w2Q8TKh69wUf-1708687884369",
    "folderPath": [],
    "confidential": {
      "projectPublicID": "71j7R0d8Z8p7E0d0n081r1e854"
    }
  }
}