{
  "accountID": "21w710Q828V8p7u0J1z9p0n3n7",
  "projectID": "f1m7R0f878N8V7g0c1w8W9u1C6",
  "tokenID": "Cr17171i1sV0od2yd4w26hH3yj4Rl7iy1Gk1EK4",
  "blockDate": 1710246347193,
  "transactionID": "Jb01zikhk6B5gQcORcFC",
  "status": "Confirmed",
  "__props__": {
    "db": "blocks",
    "collection": "Cr17171i1sV0od2yd4w26hH3yj4Rl7iy1Gk1EK4",
    "id": "P1V7v1Y0S2j4Q6q3V47701a9I3",
    "doc": "block522",
    "creationDate": 1710246347193,
    "active": true,
    "createdBy": "41V7H078W8I8I780z1m9Y2E4Y2"
  },
  "prevBlockID": "J1W7Y1m042R4766374q7v1Y9A2"
}