{
  "code": "61",
  "length": 8,
  "start": 99999999,
  "reset": "yearly",
  "end": 99999999,
  "creationDay": 1708646400000,
  "counter": 1,
  "creationDate": 1708687879760,
  "branch": "5nyQK1IEz87F9YeHrNBVqtOM9r8HFBu1dLNBXm1e9mvL4YgdweVh3ql6KPGE",
  "__props__": {
    "id": "K1d7O0T8T81817D0E0R9c2h3D7",
    "creationDate": 1708687671675,
    "collapsed": [],
    "comments": [],
    "docName": "gjoOq4xsoT7obyZE5GSpzrSSwmHbzsboEFPpgUv3R9fjh4iWF5MHviBfhcDg-1708687879760",
    "folderPath": [],
    "confidential": {
      "projectPublicID": "71j7R0d8Z8p7E0d0n081r1e854"
    }
  }
}