{
    "currency": "USD",
    "account": "ewXOe0dD5nvE5U1cgo4YcFHlrJ4kmQYeu7TpwsfmmYcmT1RaHHwnQVimWSCS-1722552298112",
    "ledgerAccount": "1/2/0",
    "credit": 10,
    "debit": 0,
    "exchangeRates": [
        {
            "code": "USD",
            "counter": 0,
            "exchangeRate": 1
        },
        {
            "code": "XOF",
            "counter": 1,
            "exchangeRate": 630
        },
        {
            "code": "LBP",
            "counter": 2,
            "exchangeRate": 89000
        },
        {
            "code": "eur",
            "counter": 4,
            "exchangeRate": 100000
        }
    ],
    "voucher": "uKFoYXSMjQA6i95YH5G3sYlJJbAQ3iGffbTOv2sWPeEoTVHB7GK7yK2w7XyQ-1722553056305",
    "voucherRef": "VCH-00000003",
    "accountBalances": [
        {
            "ledgerAccount": "1/2/0",
            "accountBalances": [
                {
                    "account": "ewXOe0dD5nvE5U1cgo4YcFHlrJ4kmQYeu7TpwsfmmYcmT1RaHHwnQVimWSCS-1722552298112",
                    "credit": 10,
                    "debit": 0,
                    "balance": -10
                }
            ]
        }
    ],
    "systemAccountBalances": [
        {
            "account": "ewXOe0dD5nvE5U1cgo4YcFHlrJ4kmQYeu7TpwsfmmYcmT1RaHHwnQVimWSCS-1722552298112",
            "credit": 10,
            "debit": 0,
            "balance": -10
        }
    ],
    "id": "DcTyI6JDCiX2gNxwVcUdpzrpVRLf23xuQk6r1uFT7nXNC3x2n7cdVtxRa1Po-1722553056283",
    "creationDate": 1722553056283,
    "creationDay": 1722546000000,
    "branch": "5nyQK1IEz87F9YeHrNBVqtOM9r8HFBu1dLNBXm1e9mvL4YgdweVh3ql6KPGE",
    "sysCredit": 10,
    "sysDebit": 0,
    "__props__": {
        "id": "q1y7c2s2C5A5K3k0G5S6q333I6",
        "doc": "transaction581",
        "counter": 581,
        "creationDate": 1722553056336,
        "collection": "transaction",
        "chunk": "chunk1",
        "lastModified": 1722553056336,
        "dev": false,
        "actions": {},
        "comments": [],
        "collapsed": [],
        "arrange": [],
        "secured": false,
        "size": 1322
    }
}