{
  "ref": "ACC-00000036",
  "ledgerAccount": "61132/1/1",
  "blockAccount": "No",
  "name": "Returnable Containers",
  "description": "Default account",
  "currency": "USD",
  "creationDay": 1710201600000,
  "creationDate": 1710239831886,
  "branch": "5nyQK1IEz87F9YeHrNBVqtOM9r8HFBu1dLNBXm1e9mvL4YgdweVh3ql6KPGE",
  "startsWith": [
    "6",
    "61",
    "611",
    "6113",
    "61132"
  ],
  "__props__": {
    "id": "W187I1t0o3B300v7A8D8l7f8h7",
    "doc": "HjFpk9P1za6M2gughSMjpAIIo3upIjwWQZeS35HP6T8KdWxkyB35zdKM2n7w-1710239831886",
    "creationDate": 1710330788787,
    "active": true,
    "createdByUserID": "41V7H078W8I8I780z1m9Y2E4Y2",
    "collapsed": [],
    "comments": [],
    "folderPath": [],
    "actions": {},
    "projectID": "f1m7R0f878N8V7g0c1w8W9u1C6",
    "counter": 652
  }
}